{
  "trends": [
    {
      "rank": 1,
      "title": "weather jammu",
      "url": "https://google.com/search?q=weather+jammu",
      "search_url": "https://google.com/search?q=weather+jammu",
      "tag": "trending"
    },
    {
      "rank": 2,
      "title": "jaipur weather",
      "url": "https://google.com/search?q=jaipur+weather",
      "search_url": "https://google.com/search?q=jaipur+weather",
      "tag": "trending"
    },
    {
      "rank": 3,
      "title": "wwe",
      "url": "https://google.com/search?q=wwe",
      "search_url": "https://google.com/search?q=wwe",
      "tag": "trending"
    },
    {
      "rank": 4,
      "title": "d.c. united vs inter miami",
      "url": "https://google.com/search?q=d.c.+united+vs+inter+miami",
      "search_url": "https://google.com/search?q=d.c.+united+vs+inter+miami",
      "tag": "trending"
    },
    {
      "rank": 5,
      "title": "bangladeshi",
      "url": "https://google.com/search?q=bangladeshi",
      "search_url": "https://google.com/search?q=bangladeshi",
      "tag": "trending"
    },
    {
      "rank": 6,
      "title": "marathi",
      "url": "https://google.com/search?q=marathi",
      "search_url": "https://google.com/search?q=marathi",
      "tag": "trending"
    },
    {
      "rank": 7,
      "title": "elon musk",
      "url": "https://google.com/search?q=elon+musk",
      "search_url": "https://google.com/search?q=elon+musk",
      "tag": "trending"
    },
    {
      "rank": 8,
      "title": "dexter resurrection",
      "url": "https://google.com/search?q=dexter+resurrection",
      "search_url": "https://google.com/search?q=dexter+resurrection",
      "tag": "trending"
    },
    {
      "rank": 9,
      "title": "srk",
      "url": "https://google.com/search?q=srk",
      "search_url": "https://google.com/search?q=srk",
      "tag": "trending"
    },
    {
      "rank": 10,
      "title": "true detective",
      "url": "https://google.com/search?q=true+detective",
      "search_url": "https://google.com/search?q=true+detective",
      "tag": "trending"
    }
  ],
  "last_updated": "2025-08-24 06:01:12 IST",
  "source": "rapidapi_realtime"
}