{
  "trends": [
    {
      "rank": 1,
      "title": "botafogo vs cear\u00e1",
      "url": "https://google.com/search?q=botafogo+vs+cear\u00e1",
      "search_url": "https://google.com/search?q=botafogo+vs+cear\u00e1",
      "tag": "trending"
    },
    {
      "rank": 2,
      "title": "u",
      "url": "https://google.com/search?q=u",
      "search_url": "https://google.com/search?q=u",
      "tag": "trending"
    },
    {
      "rank": 3,
      "title": "bing",
      "url": "https://google.com/search?q=bing",
      "search_url": "https://google.com/search?q=bing",
      "tag": "trending"
    },
    {
      "rank": 4,
      "title": "you",
      "url": "https://google.com/search?q=you",
      "search_url": "https://google.com/search?q=you",
      "tag": "trending"
    },
    {
      "rank": 5,
      "title": "brahmamudi serial",
      "url": "https://google.com/search?q=brahmamudi+serial",
      "search_url": "https://google.com/search?q=brahmamudi+serial",
      "tag": "trending"
    },
    {
      "rank": 6,
      "title": "himachal pradesh",
      "url": "https://google.com/search?q=himachal+pradesh",
      "search_url": "https://google.com/search?q=himachal+pradesh",
      "tag": "trending"
    },
    {
      "rank": 7,
      "title": "photo",
      "url": "https://google.com/search?q=photo",
      "search_url": "https://google.com/search?q=photo",
      "tag": "trending"
    },
    {
      "rank": 8,
      "title": "budimir",
      "url": "https://google.com/search?q=budimir",
      "search_url": "https://google.com/search?q=budimir",
      "tag": "trending"
    },
    {
      "rank": 9,
      "title": "lorenzo musetti",
      "url": "https://google.com/search?q=lorenzo+musetti",
      "search_url": "https://google.com/search?q=lorenzo+musetti",
      "tag": "trending"
    },
    {
      "rank": 10,
      "title": "fifa world cup 2026",
      "url": "https://google.com/search?q=fifa+world+cup+2026",
      "search_url": "https://google.com/search?q=fifa+world+cup+2026",
      "tag": "trending"
    }
  ],
  "last_updated": "2025-06-05 05:31:16 IST",
  "source": "rapidapi_realtime"
}