{
  "trends": [
    {
      "rank": 1,
      "title": "AITA for telling my (23F) boyfriend (38M) that I won\u2019t cook for him until he marries me and buys us a house?",
      "url": "https://reddit.com/r/AITA_WIBTA_PUBLIC/comments/1l0qfrm/aita_for_telling_my_23f_boyfriend_38m_that_i_wont/",
      "subreddit": "AITA_WIBTA_PUBLIC",
      "score": "3,152",
      "comments": "3,201",
      "description": "My bf and I have been together for almost 3 years and we have a 5 month old baby together. I\u2019m a SAHM, I dropped out of college to take care of him because we can\u2019t afford daycare. It was an accidental pregnancy, and abortion wasn\u2019t really an option since we live in a state where it\u2019s banned after 6...",
      "thumbnail": "",
      "author": "Valuable_Customer774",
      "created": "2025-06-01 14:35:45"
    },
    {
      "rank": 2,
      "title": "Stayed in the bathroom long enough for a shift change",
      "url": "https://reddit.com/r/WhatsWrongWithYourCat/comments/1l0xv17/stayed_in_the_bathroom_long_enough_for_a_shift/",
      "subreddit": "WhatsWrongWithYourCat",
      "score": "21,647",
      "comments": "90",
      "description": "",
      "thumbnail": "https://a.thumbs.redditmedia.com/ylsP5VWD-5pEGqY5OhoD_pubMEOV7iK8LaFEjtU_gB0.jpg",
      "author": "peachismose",
      "created": "2025-06-01 19:41:02"
    },
    {
      "rank": 3,
      "title": "34% of Russian strategic missile bombers at main airfields damaged in Ukrainian drone operation, SBU reports",
      "url": "https://reddit.com/r/worldnews/comments/1l0y47f/34_of_russian_strategic_missile_bombers_at_main/",
      "subreddit": "worldnews",
      "score": "15,899",
      "comments": "751",
      "description": "",
      "thumbnail": "https://a.thumbs.redditmedia.com/7DOp1jQvRDr2MoIFqgFu9-f6GbOP4hZucSSsJ7r0Ci0.jpg",
      "author": "Body_Languagee",
      "created": "2025-06-01 19:51:47"
    },
    {
      "rank": 4,
      "title": "AITAH for telling my girlfriend she can't force me to cancel my vacation and lose $2500 because she hates Harry Potter?",
      "url": "https://reddit.com/r/AITAH/comments/1l0ywe1/aitah_for_telling_my_girlfriend_she_cant_force_me/",
      "subreddit": "AITAH",
      "score": "3,464",
      "comments": "3,176",
      "description": "I 27M and my girlfriend 27F have been together for 4 years now. I've always wanted to visit Universal Orlando to see the Wizarding World of Harry Potter but I'd never been able to justify it financially. My dad died recently and I got an inheritance in his will, not life changing money, but enough t...",
      "thumbnail": "",
      "author": "Substantial_Run3383",
      "created": "2025-06-01 20:24:49"
    },
    {
      "rank": 5,
      "title": "A 10 second time penalty for Max is not enough. The precedent for deliberate crashes was already set in 1997.",
      "url": "https://reddit.com/r/formula1/comments/1l0qmxh/a_10_second_time_penalty_for_max_is_not_enough/",
      "subreddit": "formula1",
      "score": "15,961",
      "comments": "2,814",
      "description": "When Schumacher intentionally crashed into a driver in 1997, he was disqualified from the championship. I am not saying a penalty this harsh should be given here, but a 10s penalty is an absolute joke.\n\nMax slowed down to let George ahead, then torpedo'd him. This is undeniably a deliberate crash by...",
      "thumbnail": "",
      "author": "heyiamarandomguy",
      "created": "2025-06-01 14:44:16"
    },
    {
      "rank": 6,
      "title": "Rick then and now, 8 years later \ud83d\ude3b",
      "url": "https://reddit.com/r/aww/comments/1l0zcf1/rick_then_and_now_8_years_later/",
      "subreddit": "aww",
      "score": "12,025",
      "comments": "100",
      "description": "",
      "thumbnail": "https://b.thumbs.redditmedia.com/zCwT50K9pz4oLDOW0D7UFljFp0e6gp3TXMDUO6y6smA.jpg",
      "author": "sydbey_",
      "created": "2025-06-01 20:43:01"
    },
    {
      "rank": 7,
      "title": "Delusional Bright Light",
      "url": "https://reddit.com/r/MurderedByWords/comments/1l10nyb/delusional_bright_light/",
      "subreddit": "MurderedByWords",
      "score": "9,117",
      "comments": "77",
      "description": "",
      "thumbnail": "https://a.thumbs.redditmedia.com/woAuC0T0cEY9-q4gstddYI6XacxgmlWf1O0MHfxkug0.jpg",
      "author": "Brian_Ghoshery",
      "created": "2025-06-01 21:37:23"
    },
    {
      "rank": 8,
      "title": "Broke my hand, what games can I play without having to grab my mouse?",
      "url": "https://reddit.com/r/Steam/comments/1l0vo5w/broke_my_hand_what_games_can_i_play_without/",
      "subreddit": "Steam",
      "score": "5,513",
      "comments": "2,385",
      "description": "Its going to be a very long month.\n",
      "thumbnail": "https://b.thumbs.redditmedia.com/CuMD8wdBJiQdP_WarM1HLk4vvk0jDAjb_3lGsWJU-1I.jpg",
      "author": "JCBMHNY21",
      "created": "2025-06-01 18:11:05"
    },
    {
      "rank": 9,
      "title": "'Russian bombers are burning en masse' \u2014 Ukraine's SBU drones hit 'more than 40' aircraft in mass attack, source claims",
      "url": "https://reddit.com/r/worldnews/comments/1l0mdwj/russian_bombers_are_burning_en_masse_ukraines_sbu/",
      "subreddit": "worldnews",
      "score": "44,795",
      "comments": "2,344",
      "description": "",
      "thumbnail": "https://a.thumbs.redditmedia.com/TPPSj0rvVgAr3HVVGyZ95VRmY4FCOLcl3sdIPogNPb8.jpg",
      "author": "TheLowBro",
      "created": "2025-06-01 11:09:13"
    },
    {
      "rank": 10,
      "title": "George R. R. Martin Tells Game of Thrones Fans Who Are 'Pissed Off' He's Doing Things Other Than Writing Winds of Winter: 'You Have Given Up on Me'",
      "url": "https://reddit.com/r/books/comments/1l0vyso/george_r_r_martin_tells_game_of_thrones_fans_who/",
      "subreddit": "books",
      "score": "7,671",
      "comments": "2,280",
      "description": "",
      "thumbnail": "https://b.thumbs.redditmedia.com/QmCVdfs5GJkm9skzRlvwO9Dnvb0JPfZgmyJkKKkch3A.jpg",
      "author": "DemiFiendRSA",
      "created": "2025-06-01 18:23:07"
    },
    {
      "rank": 11,
      "title": "I photographed the Andromeda galaxy from orbit",
      "url": "https://reddit.com/r/Damnthatsinteresting/comments/1l0xq6l/i_photographed_the_andromeda_galaxy_from_orbit/",
      "subreddit": "Damnthatsinteresting",
      "score": "18,069",
      "comments": "246",
      "description": "",
      "thumbnail": "https://b.thumbs.redditmedia.com/bYta6Wv6bMioVrvIjjzl-6QxAGCaYdpnx2yR-lUnv3E.jpg",
      "author": "astro_pettit",
      "created": "2025-06-01 19:35:23"
    },
    {
      "rank": 12,
      "title": "Full auto integrally suppressed Glock 44",
      "url": "https://reddit.com/r/interestingasfuck/comments/1l0tdv0/full_auto_integrally_suppressed_glock_44/",
      "subreddit": "interestingasfuck",
      "score": "31,373",
      "comments": "2,143",
      "description": "",
      "thumbnail": "https://external-preview.redd.it/eXpoMXozbHpmYzRmMa56zU73INp4CfAY1M9wg4sD79zTZyhkr4hNQg0L3ZNX.png?width=140&amp;height=140&amp;crop=140:140,smart&amp;format=jpg&amp;v=enabled&amp;lthumb=true&amp;s=409b7d69ba50119ea321115df68df5cdac042f0e",
      "author": "HANAEMILK",
      "created": "2025-06-01 16:37:58"
    },
    {
      "rank": 13,
      "title": "Why are Mexicans stereotyped as lazy when everyone says they're very hardworking?",
      "url": "https://reddit.com/r/NoStupidQuestions/comments/1l0qj1q/why_are_mexicans_stereotyped_as_lazy_when/",
      "subreddit": "NoStupidQuestions",
      "score": "6,649",
      "comments": "2,120",
      "description": "",
      "thumbnail": "",
      "author": "Odd-Tangerine9584",
      "created": "2025-06-01 14:39:34"
    },
    {
      "rank": 14,
      "title": "Tis the Season [OC]",
      "url": "https://reddit.com/r/comics/comments/1l0xi46/tis_the_season_oc/",
      "subreddit": "comics",
      "score": "23,386",
      "comments": "296",
      "description": "",
      "thumbnail": "https://b.thumbs.redditmedia.com/2LtaQbvIc7kIqKV4FvNif1Y_rZYM3tgqWlHf2i3hxlc.jpg",
      "author": "TheRealHolleringElk",
      "created": "2025-06-01 19:25:52"
    },
    {
      "rank": 15,
      "title": "This is why they hate tourists",
      "url": "https://reddit.com/r/mildlyinfuriating/comments/1l0q1wg/this_is_why_they_hate_tourists/",
      "subreddit": "mildlyinfuriating",
      "score": "28,177",
      "comments": "1,937",
      "description": "",
      "thumbnail": "https://external-preview.redd.it/cGJjdmtjejNyYjRmMdTWPQkOOEfhKg9LwIIP7GfnT3djuQ6WlrFkSXvaqb5I.png?width=140&amp;height=140&amp;crop=140:140,smart&amp;format=jpg&amp;v=enabled&amp;lthumb=true&amp;s=2bc1cb751e014f0578e26631c1ed71fc0d8773c7",
      "author": "rgatoNacho",
      "created": "2025-06-01 14:18:29"
    },
    {
      "rank": 16,
      "title": "A tattoo that glows under ultraviolet light.",
      "url": "https://reddit.com/r/nextfuckinglevel/comments/1l10wwf/a_tattoo_that_glows_under_ultraviolet_light/",
      "subreddit": "nextfuckinglevel",
      "score": "8,542",
      "comments": "537",
      "description": "",
      "thumbnail": "https://external-preview.redd.it/OGw4dmlzdmN6ZDRmMX89kQNDYwkcR8Ly5PqtHhDOyYdPfsMq2Tm_7oSZSgB0.png?width=140&amp;height=140&amp;crop=140:140,smart&amp;format=jpg&amp;v=enabled&amp;lthumb=true&amp;s=9a2b52ef1eb8646fc95187a006c12951d25bb39a",
      "author": "BrushAggravating6414",
      "created": "2025-06-01 21:48:16"
    },
    {
      "rank": 17,
      "title": "Trump was not informed of Ukraine attack on Russia",
      "url": "https://reddit.com/r/politics/comments/1l0vp16/trump_was_not_informed_of_ukraine_attack_on_russia/",
      "subreddit": "politics",
      "score": "16,088",
      "comments": "1,314",
      "description": "",
      "thumbnail": "https://b.thumbs.redditmedia.com/NQYWIspsyLlRQxrFqFyXzdsw2rqJLIUEU2lfyy0LBeo.jpg",
      "author": "sunnysidejacqueline",
      "created": "2025-06-01 18:12:02"
    },
    {
      "rank": 18,
      "title": "Chris shares new photo with JoJo. If I have to see it, so do you",
      "url": "https://reddit.com/r/Fauxmoi/comments/1l0u7dy/chris_shares_new_photo_with_jojo_if_i_have_to_see/",
      "subreddit": "Fauxmoi",
      "score": "5,994",
      "comments": "1,860",
      "description": "",
      "thumbnail": "https://b.thumbs.redditmedia.com/MrPbWXhNqk1A-CqimvMD1T4TX7VnAOEogm4tBwEulGU.jpg",
      "author": "LeonOkada9",
      "created": "2025-06-01 17:11:27"
    },
    {
      "rank": 19,
      "title": "Bought a Lego Technic at Costco and the same car was in the Parking lot",
      "url": "https://reddit.com/r/mildlyinteresting/comments/1l0y0zu/bought_a_lego_technic_at_costco_and_the_same_car/",
      "subreddit": "mildlyinteresting",
      "score": "10,598",
      "comments": "214",
      "description": "",
      "thumbnail": "https://b.thumbs.redditmedia.com/tRHx2mcOaLwYCeTUpZtlBIIEJYSoRPg-89dXVCd7zTU.jpg",
      "author": "_nenena",
      "created": "2025-06-01 19:47:57"
    },
    {
      "rank": 20,
      "title": "Britney Spears\u2019 motivation for shaving her head actually made complete sense.",
      "url": "https://reddit.com/r/Fauxmoi/comments/1l0wht0/britney_spears_motivation_for_shaving_her_head/",
      "subreddit": "Fauxmoi",
      "score": "13,581",
      "comments": "318",
      "description": "",
      "thumbnail": "https://external-preview.redd.it/cXFkeDM0cmsyZDRmMRd7St18w2yqPFsTLY_GFZ6XSv1zPwFx96_oZHvh8NSo.png?width=140&amp;height=140&amp;crop=140:140,smart&amp;format=jpg&amp;v=enabled&amp;lthumb=true&amp;s=1159f243ddaece76723442a98ac9f46025d85eb9",
      "author": "vogueindex",
      "created": "2025-06-01 18:44:30"
    },
    {
      "rank": 21,
      "title": "Meirl",
      "url": "https://reddit.com/r/meirl/comments/1l0ufus/meirl/",
      "subreddit": "meirl",
      "score": "27,455",
      "comments": "298",
      "description": "",
      "thumbnail": "https://b.thumbs.redditmedia.com/miEha3xAGZsZzGiR_Fsb0P29suifB3sxxnIgUH4Qyys.jpg",
      "author": "JaredOlsen8791",
      "created": "2025-06-01 17:21:09"
    },
    {
      "rank": 22,
      "title": "Woke up to find this on my kitchen floor.. I live alone and don\u2019t own any board games\u2026",
      "url": "https://reddit.com/r/Weird/comments/1l0q6ma/woke_up_to_find_this_on_my_kitchen_floor_i_live/",
      "subreddit": "Weird",
      "score": "10,295",
      "comments": "1,618",
      "description": "",
      "thumbnail": "https://b.thumbs.redditmedia.com/XOO3oJhF83_PUXwrYdM-yHPZSlYvZL3DrmpVeJTH2DA.jpg",
      "author": "fastRabbit",
      "created": "2025-06-01 14:24:24"
    },
    {
      "rank": 23,
      "title": "She Got an Abortion. So A Texas Cop Used 83,000 Cameras to Track Her Down",
      "url": "https://reddit.com/r/technology/comments/1l0to98/she_got_an_abortion_so_a_texas_cop_used_83000/",
      "subreddit": "technology",
      "score": "26,390",
      "comments": "1,598",
      "description": "",
      "thumbnail": "https://b.thumbs.redditmedia.com/BsQSDw2KZDyU-eFB8SYdFnhvw0_ZV_vFuggABvmFFEU.jpg",
      "author": "zrv8psgOS9AiWK6ugbt2",
      "created": "2025-06-01 16:49:48"
    },
    {
      "rank": 24,
      "title": "Ron Killings: \"Im sorry to inform you all. I just got released from WWE. I want to thank WWE for the ride, but MOSTLY I want to thank each and EVERYONE OF YOU who was along for the ride, Thank you for all the love, support, and appreciation you have given me over the years. Thank you \ud83d\ude4f\ud83c\udffe \"",
      "url": "https://reddit.com/r/SquaredCircle/comments/1l0rf21/ron_killings_im_sorry_to_inform_you_all_i_just/",
      "subreddit": "SquaredCircle",
      "score": "7,484",
      "comments": "1,507",
      "description": "",
      "thumbnail": "",
      "author": "R0DAN",
      "created": "2025-06-01 15:16:59"
    },
    {
      "rank": 25,
      "title": "Meirl",
      "url": "https://reddit.com/r/meirl/comments/1l0mh3i/meirl/",
      "subreddit": "meirl",
      "score": "60,505",
      "comments": "1,486",
      "description": "",
      "thumbnail": "https://b.thumbs.redditmedia.com/2R22U5D83QMcj6R-0U7pWkl7nRG4GgE_qdh20E8VdZU.jpg",
      "author": "Afraid-Objective3049",
      "created": "2025-06-01 11:14:41"
    }
  ],
  "last_updated": "2025-06-02 05:31:26 IST"
}