{
  "trends": [
    {
      "rank": 1,
      "name": "#CSKvsMI",
      "url": "https://twitter.com/search?q=%23CSKvsMI",
      "volume": "49.0k+",
      "tag": "trending"
    },
    {
      "rank": 2,
      "name": "Happy Easter",
      "url": "https://twitter.com/search?q=Happy Easter",
      "volume": "-",
      "tag": "trending"
    },
    {
      "rank": 3,
      "name": "#NishikantDubey",
      "url": "https://twitter.com/search?q=%23NishikantDubey",
      "volume": "33.0k+",
      "tag": "trending"
    },
    {
      "rank": 4,
      "name": "#PBKSvRCB",
      "url": "https://twitter.com/search?q=%23PBKSvRCB",
      "volume": "26.0k+",
      "tag": "trending"
    },
    {
      "rank": 5,
      "name": "Nadda",
      "url": "https://twitter.com/search?q=Nadda",
      "volume": "35.0k+",
      "tag": "trending"
    },
    {
      "rank": 6,
      "name": "#RohitSharma",
      "url": "https://twitter.com/search?q=%23RohitSharma",
      "volume": "18.0k+",
      "tag": "trending"
    },
    {
      "rank": 7,
      "name": "Ayush Mhatre",
      "url": "https://twitter.com/search?q=Ayush Mhatre",
      "volume": "31.0k+",
      "tag": "trending"
    },
    {
      "rank": 8,
      "name": "Jadeja",
      "url": "https://twitter.com/search?q=Jadeja",
      "volume": "22.0k+",
      "tag": "trending"
    },
    {
      "rank": 9,
      "name": "Valverde",
      "url": "https://twitter.com/search?q=Valverde",
      "volume": "78.0k+",
      "tag": "trending"
    },
    {
      "rank": 10,
      "name": "Fake Kathavachak",
      "url": "https://twitter.com/search?q=Fake Kathavachak",
      "volume": "78.0k+",
      "tag": "trending"
    },
    {
      "rank": 11,
      "name": "elvish ruling roadies",
      "url": "https://twitter.com/search?q=elvish ruling roadies",
      "volume": "23.0k+",
      "tag": "trending"
    },
    {
      "rank": 12,
      "name": "Ramban",
      "url": "https://twitter.com/search?q=Ramban",
      "volume": "-",
      "tag": "trending"
    },
    {
      "rank": 13,
      "name": "avesh khan",
      "url": "https://twitter.com/search?q=avesh khan",
      "volume": "-",
      "tag": "trending"
    },
    {
      "rank": 14,
      "name": "Nupur Sharma",
      "url": "https://twitter.com/search?q=Nupur Sharma",
      "volume": "17.0k+",
      "tag": "trending"
    },
    {
      "rank": 15,
      "name": "Wankhede",
      "url": "https://twitter.com/search?q=Wankhede",
      "volume": "27.0k+",
      "tag": "trending"
    },
    {
      "rank": 16,
      "name": "Bianca",
      "url": "https://twitter.com/search?q=Bianca",
      "volume": "108.0k+",
      "tag": "trending"
    },
    {
      "rank": 17,
      "name": "Padikkal",
      "url": "https://twitter.com/search?q=Padikkal",
      "volume": "14.0k+",
      "tag": "trending"
    },
    {
      "rank": 18,
      "name": "Hitman",
      "url": "https://twitter.com/search?q=Hitman",
      "volume": "20.0k+",
      "tag": "trending"
    },
    {
      "rank": 19,
      "name": "abd villiers",
      "url": "https://twitter.com/search?q=abd villiers",
      "volume": "-",
      "tag": "trending"
    },
    {
      "rank": 20,
      "name": "Santner",
      "url": "https://twitter.com/search?q=Santner",
      "volume": "-",
      "tag": "trending"
    },
    {
      "rank": 21,
      "name": "j. buttler",
      "url": "https://twitter.com/search?q=j. buttler",
      "volume": "-",
      "tag": "trending"
    },
    {
      "rank": 22,
      "name": "s. fleming",
      "url": "https://twitter.com/search?q=s. fleming",
      "volume": "-",
      "tag": "trending"
    },
    {
      "rank": 23,
      "name": "jaddu",
      "url": "https://twitter.com/search?q=jaddu",
      "volume": "-",
      "tag": "trending"
    },
    {
      "rank": 24,
      "name": "m. jayawardene",
      "url": "https://twitter.com/search?q=m. jayawardene",
      "volume": "-",
      "tag": "trending"
    },
    {
      "rank": 25,
      "name": "Vini",
      "url": "https://twitter.com/search?q=Vini",
      "volume": "40.0k+",
      "tag": "trending"
    },
    {
      "rank": 26,
      "name": "Rachin",
      "url": "https://twitter.com/search?q=Rachin",
      "volume": "-",
      "tag": "trending"
    },
    {
      "rank": 27,
      "name": "Paul Heyman",
      "url": "https://twitter.com/search?q=Paul Heyman",
      "volume": "77.0k+",
      "tag": "trending"
    },
    {
      "rank": 28,
      "name": "Trent",
      "url": "https://twitter.com/search?q=Trent",
      "volume": "57.0k+",
      "tag": "trending"
    },
    {
      "rank": 29,
      "name": "He is Risen",
      "url": "https://twitter.com/search?q=He is Risen",
      "volume": "411.0k+",
      "tag": "trending"
    },
    {
      "rank": 30,
      "name": "m. vijay",
      "url": "https://twitter.com/search?q=m. vijay",
      "volume": "-",
      "tag": "trending"
    },
    {
      "rank": 31,
      "name": "Bhuvi",
      "url": "https://twitter.com/search?q=Bhuvi",
      "volume": "11.0k+",
      "tag": "trending"
    },
    {
      "rank": 32,
      "name": "Romario",
      "url": "https://twitter.com/search?q=Romario",
      "volume": "11.0k+",
      "tag": "trending"
    },
    {
      "rank": 33,
      "name": "Kannada",
      "url": "https://twitter.com/search?q=Kannada",
      "volume": "15.0k+",
      "tag": "trending"
    },
    {
      "rank": 34,
      "name": "Kamboj",
      "url": "https://twitter.com/search?q=Kamboj",
      "volume": "-",
      "tag": "trending"
    },
    {
      "rank": 35,
      "name": "Brahmins",
      "url": "https://twitter.com/search?q=Brahmins",
      "volume": "11.0k+",
      "tag": "trending"
    },
    {
      "rank": 36,
      "name": "Jain",
      "url": "https://twitter.com/search?q=Jain",
      "volume": "17.0k+",
      "tag": "trending"
    },
    {
      "rank": 37,
      "name": "Charles",
      "url": "https://twitter.com/search?q=Charles",
      "volume": "146.0k+",
      "tag": "trending"
    },
    {
      "rank": 38,
      "name": "Dhoni",
      "url": "https://twitter.com/search?q=Dhoni",
      "volume": "55.0k+",
      "tag": "trending"
    },
    {
      "rank": 39,
      "name": "ARRESTED",
      "url": "https://twitter.com/search?q=ARRESTED",
      "volume": "198.0k+",
      "tag": "trending"
    },
    {
      "rank": 40,
      "name": "#CSKvsMI",
      "url": "https://twitter.com/search?q=%23CSKvsMI",
      "volume": "48.0k+",
      "tag": "trending"
    },
    {
      "rank": 41,
      "name": "Happy Easter",
      "url": "https://twitter.com/search?q=Happy Easter",
      "volume": "-",
      "tag": "trending"
    },
    {
      "rank": 42,
      "name": "#NishikantDubey",
      "url": "https://twitter.com/search?q=%23NishikantDubey",
      "volume": "33.0k+",
      "tag": "trending"
    },
    {
      "rank": 43,
      "name": "#PBKSvRCB",
      "url": "https://twitter.com/search?q=%23PBKSvRCB",
      "volume": "25.0k+",
      "tag": "trending"
    },
    {
      "rank": 44,
      "name": "Nadda",
      "url": "https://twitter.com/search?q=Nadda",
      "volume": "35.0k+",
      "tag": "trending"
    },
    {
      "rank": 45,
      "name": "#RohitSharma",
      "url": "https://twitter.com/search?q=%23RohitSharma",
      "volume": "18.0k+",
      "tag": "trending"
    },
    {
      "rank": 46,
      "name": "Ayush Mhatre",
      "url": "https://twitter.com/search?q=Ayush Mhatre",
      "volume": "31.0k+",
      "tag": "trending"
    },
    {
      "rank": 47,
      "name": "Jadeja",
      "url": "https://twitter.com/search?q=Jadeja",
      "volume": "22.0k+",
      "tag": "trending"
    },
    {
      "rank": 48,
      "name": "Valverde",
      "url": "https://twitter.com/search?q=Valverde",
      "volume": "74.0k+",
      "tag": "trending"
    },
    {
      "rank": 49,
      "name": "Fake Kathavachak",
      "url": "https://twitter.com/search?q=Fake Kathavachak",
      "volume": "80.0k+",
      "tag": "trending"
    },
    {
      "rank": 50,
      "name": "elvish ruling roadies",
      "url": "https://twitter.com/search?q=elvish ruling roadies",
      "volume": "23.0k+",
      "tag": "trending"
    },
    {
      "rank": 51,
      "name": "Ramban",
      "url": "https://twitter.com/search?q=Ramban",
      "volume": "-",
      "tag": "trending"
    },
    {
      "rank": 52,
      "name": "avesh khan",
      "url": "https://twitter.com/search?q=avesh khan",
      "volume": "-",
      "tag": "trending"
    },
    {
      "rank": 53,
      "name": "Nupur Sharma",
      "url": "https://twitter.com/search?q=Nupur Sharma",
      "volume": "16.0k+",
      "tag": "trending"
    },
    {
      "rank": 54,
      "name": "Wankhede",
      "url": "https://twitter.com/search?q=Wankhede",
      "volume": "27.0k+",
      "tag": "trending"
    },
    {
      "rank": 55,
      "name": "Dhoni",
      "url": "https://twitter.com/search?q=Dhoni",
      "volume": "55.0k+",
      "tag": "trending"
    },
    {
      "rank": 56,
      "name": "Padikkal",
      "url": "https://twitter.com/search?q=Padikkal",
      "volume": "14.0k+",
      "tag": "trending"
    },
    {
      "rank": 57,
      "name": "Oscar",
      "url": "https://twitter.com/search?q=Oscar",
      "volume": "142.0k+",
      "tag": "trending"
    },
    {
      "rank": 58,
      "name": "Hitman",
      "url": "https://twitter.com/search?q=Hitman",
      "volume": "20.0k+",
      "tag": "trending"
    },
    {
      "rank": 59,
      "name": "ABD Villiers",
      "url": "https://twitter.com/search?q=ABD Villiers",
      "volume": "-",
      "tag": "trending"
    },
    {
      "rank": 60,
      "name": "Rachin",
      "url": "https://twitter.com/search?q=Rachin",
      "volume": "-",
      "tag": "trending"
    },
    {
      "rank": 61,
      "name": "Santner",
      "url": "https://twitter.com/search?q=Santner",
      "volume": "-",
      "tag": "trending"
    },
    {
      "rank": 62,
      "name": "J. Buttler",
      "url": "https://twitter.com/search?q=J. Buttler",
      "volume": "-",
      "tag": "trending"
    },
    {
      "rank": 63,
      "name": "S. Fleming",
      "url": "https://twitter.com/search?q=S. Fleming",
      "volume": "-",
      "tag": "trending"
    },
    {
      "rank": 64,
      "name": "Jaddu",
      "url": "https://twitter.com/search?q=Jaddu",
      "volume": "-",
      "tag": "trending"
    },
    {
      "rank": 65,
      "name": "M. Jayawardene",
      "url": "https://twitter.com/search?q=M. Jayawardene",
      "volume": "-",
      "tag": "trending"
    },
    {
      "rank": 66,
      "name": "Vini",
      "url": "https://twitter.com/search?q=Vini",
      "volume": "40.0k+",
      "tag": "trending"
    },
    {
      "rank": 67,
      "name": "Paul Heyman",
      "url": "https://twitter.com/search?q=Paul Heyman",
      "volume": "76.0k+",
      "tag": "trending"
    },
    {
      "rank": 68,
      "name": "Trent",
      "url": "https://twitter.com/search?q=Trent",
      "volume": "56.0k+",
      "tag": "trending"
    },
    {
      "rank": 69,
      "name": "Kannada",
      "url": "https://twitter.com/search?q=Kannada",
      "volume": "15.0k+",
      "tag": "trending"
    },
    {
      "rank": 70,
      "name": "He is Risen",
      "url": "https://twitter.com/search?q=He is Risen",
      "volume": "401.0k+",
      "tag": "trending"
    },
    {
      "rank": 71,
      "name": "M. Vijay",
      "url": "https://twitter.com/search?q=M. Vijay",
      "volume": "-",
      "tag": "trending"
    },
    {
      "rank": 72,
      "name": "Bhuvi",
      "url": "https://twitter.com/search?q=Bhuvi",
      "volume": "11.0k+",
      "tag": "trending"
    },
    {
      "rank": 73,
      "name": "Romario",
      "url": "https://twitter.com/search?q=Romario",
      "volume": "12.0k+",
      "tag": "trending"
    },
    {
      "rank": 74,
      "name": "Kamboj",
      "url": "https://twitter.com/search?q=Kamboj",
      "volume": "-",
      "tag": "trending"
    },
    {
      "rank": 75,
      "name": "Brahmins",
      "url": "https://twitter.com/search?q=Brahmins",
      "volume": "12.0k+",
      "tag": "trending"
    },
    {
      "rank": 76,
      "name": "Jain",
      "url": "https://twitter.com/search?q=Jain",
      "volume": "17.0k+",
      "tag": "trending"
    },
    {
      "rank": 77,
      "name": "Charles",
      "url": "https://twitter.com/search?q=Charles",
      "volume": "144.0k+",
      "tag": "trending"
    },
    {
      "rank": 78,
      "name": "POTM",
      "url": "https://twitter.com/search?q=POTM",
      "volume": "14.0k+",
      "tag": "trending"
    }
  ],
  "last_updated": "2025-04-21 06:30:52 IST"
}