{
  "trends": [
    {
      "rank": 1,
      "title": "HIT 3 Telugu Trailer | Nani | Sailesh Kolanu | Srinidhi Shetty | In Cinemas May 1st",
      "channel": "Wall Poster Cinema",
      "views": "23.0M",
      "likes": "467.3k",
      "url": "https://youtube.com/watch?v=kAtfaaUgDRU",
      "tag": "trending"
    },
    {
      "rank": 2,
      "title": "Comedy is Difficult - Standup Comedy by Varun Grover",
      "channel": "Varun Grover",
      "views": "701.2k",
      "likes": "44.9k",
      "url": "https://youtube.com/watch?v=S9NFCNDtjDU",
      "tag": "trending"
    },
    {
      "rank": 3,
      "title": "A SURPRISE VISIT TO MY HOME | FORTUNER \u2764\ufe0f",
      "channel": "Praveen Pranav",
      "views": "2.5M",
      "likes": "149.9k",
      "url": "https://youtube.com/watch?v=cQwBz12AXdM",
      "tag": "trending"
    },
    {
      "rank": 4,
      "title": "EMIWAY BANTAI X YOUNG GALIB - JOSH MEI | (PROD BY  MEMAX) | OFFICIAL MUSIC VIDEO",
      "channel": "Emiway Bantai",
      "views": "1.1M",
      "likes": "156.9k",
      "url": "https://youtube.com/watch?v=tQXP-vtjjno",
      "tag": "trending"
    },
    {
      "rank": 5,
      "title": "Parwarish Episode 3 | Aina Asif | Samar Jafri | 14 April 2025 (Eng Sub) ARY Digital Drama",
      "channel": "ARY Digital HD",
      "views": "5.2M",
      "likes": "92.2k",
      "url": "https://youtube.com/watch?v=M5rJhdRClNM",
      "tag": "trending"
    },
    {
      "rank": 6,
      "title": "Poyivaa Nanba (Tamil) Song Promo | Kuberaa | Dhanush, Nagarjuna, Rashmika | Sekhar Kammula | DSP",
      "channel": "Aditya Music Tamil",
      "views": "611.2k",
      "likes": "25.3k",
      "url": "https://youtube.com/watch?v=K-9L4oEvE9I",
      "tag": "trending"
    },
    {
      "rank": 7,
      "title": "I Gifted Poor family a NEW HOUSE \ud83d\ude0d",
      "channel": "Fukra Insaan",
      "views": "6.3M",
      "likes": "725.2k",
      "url": "https://youtube.com/watch?v=VofVOZlVADY",
      "tag": "trending"
    },
    {
      "rank": 8,
      "title": "Judwaa - Episode 33 - 15th April 2025 [ Aina Asif & Adnan Raza Mir ] BERG OYSTER PEARL - HUM TV",
      "channel": "HUM TV",
      "views": "14.2M",
      "likes": "275.2k",
      "url": "https://youtube.com/watch?v=Rzo9JKkTLqw",
      "tag": "trending"
    },
    {
      "rank": 9,
      "title": "Parwarish Episode 4 | Aina Asif | Samar Jafri | 15 April 2025 (Eng Sub) ARY Digital Drama",
      "channel": "ARY Digital HD",
      "views": "3.8M",
      "likes": "80.0k",
      "url": "https://youtube.com/watch?v=V2AwWQInGB8",
      "tag": "trending"
    },
    {
      "rank": 10,
      "title": "Jewel Thief - The Heist Begins | Saif Ali Khan, Jaideep Ahlawat | Official Trailer | Netflix",
      "channel": "Netflix India",
      "views": "14.7M",
      "likes": "55.8k",
      "url": "https://youtube.com/watch?v=_dUNLPNfS8s",
      "tag": "trending"
    },
    {
      "rank": 11,
      "title": "\u0d15\u0d23\u0d4d\u0d1f\u0d15\u0d3e\u0d30\u0d4d\u0d2f\u0d02 \u0d1f\u0d3e\u0d7c\u0d38\u0d3f\u0d2f\u0d42\u0d38\u0d4d \u0d0e\u0d35\u0d3f\u0d1f\u0d46\u0d2f\u0d41\u0d02 \u0d2a\u0d31\u0d2f\u0d41\u0d02",
      "channel": "OPM Records",
      "views": "154.2k",
      "likes": "1.4k",
      "url": "https://youtube.com/watch?v=uRFyN0IZenM",
      "tag": "trending"
    },
    {
      "rank": 12,
      "title": "Motorola Edge 60 Stylus Unboxing & First Look \u26a1 Stylus, IP68, Wireless Charging @ \u20b921,999*!",
      "channel": "Trakin Tech",
      "views": "1.2M",
      "likes": "36.4k",
      "url": "https://youtube.com/watch?v=7l8zzIyCm40",
      "tag": "trending"
    },
    {
      "rank": 13,
      "title": "Are Companies Cheating Us? | Dreamz Unlimited | Consumer Protection",
      "channel": "Dreamz Unlimited",
      "views": "231.5k",
      "likes": "24.6k",
      "url": "https://youtube.com/watch?v=krstyl87etQ",
      "tag": "trending"
    },
    {
      "rank": 14,
      "title": "Panipuri Bandi | \u0c1a\u0c02\u0c26\u0c41 \u0c2a\u0c3e\u0c28\u0c3f\u0c2a\u0c42\u0c30\u0c3f \u0c2c\u0c02\u0c21\u0c3f | Gupchup | Golgappa | Bhelpuri | My Village Show | Gangavva",
      "channel": "Village Show - Mix",
      "views": "296.9k",
      "likes": "8.3k",
      "url": "https://youtube.com/watch?v=AgRFdYFnzP4",
      "tag": "trending"
    },
    {
      "rank": 15,
      "title": "Vijayashanti & Kalyan Ram Interview With Teenmaar Chandravva | Arjun Son Of Vyjayanthi | V6Ent",
      "channel": "V6 Entertainment",
      "views": "106.6k",
      "likes": "1.6k",
      "url": "https://youtube.com/watch?v=8nZ9c2mO4G8",
      "tag": "trending"
    },
    {
      "rank": 16,
      "title": "#Video - #Khesari Lal Yadav | \u0921\u0930 \u0932\u093e\u0917\u0947 \u0938\u091f\u0932\u093e \u092aS | #Shilpi Raj | Dar Lage Satla Pa | Bhojpuri Song GMJ",
      "channel": "GMJ - Global Music Junction - Bhojpuri",
      "views": "516.5k",
      "likes": "37.7k",
      "url": "https://youtube.com/watch?v=LV4wWpMzxeY",
      "tag": "trending"
    },
    {
      "rank": 17,
      "title": "\u0c2c\u0c47\u0c15\u0c4d \u0c1a\u0c47\u0c38\u0c47 \u0c2a\u0c28\u0c3f \u0c32\u0c47\u0c15\u0c41\u0c02\u0c21\u0c3e \u0c2a\u0c3f\u0c32\u0c4d\u0c32\u0c32\u0c41 \u0c38\u0c4d\u0c35\u0c40\u0c1f\u0c4d \u0c05\u0c21\u0c3f\u0c17\u0c3f\u0c28\u0c2a\u0c4d\u0c2a\u0c41\u0c21\u0c41 10 \u0c28\u0c3f\u0c2e\u0c3f\u0c37\u0c3e\u0c32\u0c4d\u0c32\u0c4b \u0c38\u0c3e\u0c2b\u0c4d\u0c1f\u0c4d \u0c17\u0c3e \u0c09\u0c02\u0c21\u0c47 \u0c08 \u0c15\u0c47\u0c15\u0c4d \u0c1a\u0c47\u0c38\u0c3f \u0c2a\u0c46\u0c1f\u0c4d\u0c1f\u0c02\u0c21\u0c3f",
      "channel": "Welcome to aswini kitchen.",
      "views": "214.7k",
      "likes": "2.5k",
      "url": "https://youtube.com/watch?v=rzndNWB7S3I",
      "tag": "trending"
    },
    {
      "rank": 18,
      "title": "Poracha Bajar Uthala Ra  | Song Out Now | Suraj Chavan | Jui Bhagwat | Kedar Shinde | 25 April 2025",
      "channel": "JioStudios",
      "views": "310.9k",
      "likes": "11.1k",
      "url": "https://youtube.com/watch?v=i3FHHevlT7Q",
      "tag": "trending"
    },
    {
      "rank": 19,
      "title": "Patharamattu Promo || 16-04-2025 || Episode 605 || Asianet",
      "channel": "Asianet",
      "views": "461.4k",
      "likes": "6.1k",
      "url": "https://youtube.com/watch?v=bycsfWMxEzI",
      "tag": "trending"
    },
    {
      "rank": 20,
      "title": "Ishq | Nakkalites",
      "channel": "Nakkalites",
      "views": "127.8k",
      "likes": "5.7k",
      "url": "https://youtube.com/watch?v=V0pzjaRG9Gs",
      "tag": "trending"
    },
    {
      "rank": 21,
      "title": "Judwaa - Episode 32 - 14th April 2025 [ Aina Asif & Adnan Raza Mir ] BERG OYSTER PEARL - HUM TV",
      "channel": "HUM TV",
      "views": "16.2M",
      "likes": "280.9k",
      "url": "https://youtube.com/watch?v=U3I0L2_7PII",
      "tag": "trending"
    },
    {
      "rank": 22,
      "title": "SINKY Weds ROSHEN \u2764\ufe0f WEDDING VLOG | Part-1",
      "channel": "Roshens Vlog",
      "views": "200.2k",
      "likes": "4.6k",
      "url": "https://youtube.com/watch?v=Rv6f688AT_o",
      "tag": "trending"
    },
    {
      "rank": 23,
      "title": "Rong Oi Rongali - Achurjya Borpatra | Sunit Gogoi | Pankaj Bora | New Bihu 2025",
      "channel": "Achurjya Borpatra Official",
      "views": "375.5k",
      "likes": "7.9k",
      "url": "https://youtube.com/watch?v=5rCSYRhyHgM",
      "tag": "trending"
    },
    {
      "rank": 24,
      "title": "Masala Bread Toast Recipe in Tamil | Bread Recipes in Tamil",
      "channel": "Madras Samayal",
      "views": "140.9k",
      "likes": "4.2k",
      "url": "https://youtube.com/watch?v=oH4uIG__Gm4",
      "tag": "trending"
    },
    {
      "rank": 25,
      "title": "Vadivelu Comedy Compilations | Chandramukhi 2 | Raghawa Lawarnce | Kangana | P Vasu  | Vadivelu",
      "channel": "Lyca Productions",
      "views": "122.2k",
      "likes": "1.3k",
      "url": "https://youtube.com/watch?v=IFN9uQflfd8",
      "tag": "trending"
    },
    {
      "rank": 26,
      "title": "Aaj Din Chadheya - Lyrical Video | Saif Ali Khan, Deepika P | Love Aaj Kal | Rahat Fateh Ali Khan",
      "channel": "Eros Now Music",
      "views": "172.4k",
      "likes": "1.8k",
      "url": "https://youtube.com/watch?v=IImcBEHuDRI",
      "tag": "trending"
    },
    {
      "rank": 27,
      "title": "\u0915\u094d\u092f\u094b\u0902 \u0939\u092e\u0947 \u091c\u0940\u0924\u0947 \u091c\u0940 \u092e\u093e\u0930 \u0921\u093e\u0932\u0928\u093e \u091a\u093e\u0939\u0924\u0940 \u0939\u0948\u0902 Prem Granth Movie Scene - Madhuri - Sulbha Arya - Om Puri",
      "channel": "Ultra Bollywood",
      "views": "2.6M",
      "likes": "6.6k",
      "url": "https://youtube.com/watch?v=gmi9gJyZibg",
      "tag": "trending"
    },
    {
      "rank": 28,
      "title": "Ye Color Pasand Aagya \ud83d\ude0d New Car ka",
      "channel": "Sourav Joshi Vlogs",
      "views": "3.6M",
      "likes": "168.8k",
      "url": "https://youtube.com/watch?v=qpJfCJnf2hU",
      "tag": "trending"
    },
    {
      "rank": 29,
      "title": "Judwaa - Episode 34 Teaser - 15 Apr 25 [ Aina Asif & Adnan Raza Mir ] BERG OYSTER PEARL - HUM TV",
      "channel": "HUM TV",
      "views": "3.8M",
      "likes": "41.2k",
      "url": "https://youtube.com/watch?v=r4fTm3Udrgg",
      "tag": "trending"
    },
    {
      "rank": 30,
      "title": "Domestic Violence In Village | Nakkalites Fzone",
      "channel": "Nakkalites FZone",
      "views": "726.7k",
      "likes": "22.5k",
      "url": "https://youtube.com/watch?v=6luzIiEWIWI",
      "tag": "trending"
    }
  ],
  "last_updated": "2025-04-17 01:42:28 IST"
}