{
  "trends": [
    {
      "rank": 1,
      "title": "LAAL PARI (Song): Yo Yo Honey Singh | Sajid Nadiadwala | Tarun Mansukhani | Housefull 5 - 6th June",
      "channel": "T-Series",
      "views": "26.7M",
      "likes": "613.5k",
      "url": "https://youtube.com/watch?v=KGn-erOG-Bs",
      "tag": "trending"
    },
    {
      "rank": 2,
      "title": "Saying YES to Ruchika for 24 HOURS",
      "channel": "Triggered Insaan",
      "views": "4.8M",
      "likes": "392.3k",
      "url": "https://youtube.com/watch?v=bI3_3PX6PjQ",
      "tag": "trending"
    },
    {
      "rank": 3,
      "title": "Mummy Aur Shopping | Zakir Khan | Stand Up Comedy | Sukha Puri 9",
      "channel": "Zakir Khan",
      "views": "1.8M",
      "likes": "96.4k",
      "url": "https://youtube.com/watch?v=-7TxYcgioxg",
      "tag": "trending"
    },
    {
      "rank": 4,
      "title": "BroCode Roast Ft. @raviguptacomedy  | S2. Ep1",
      "channel": "Aashish Solanki",
      "views": "3.8M",
      "likes": "173.5k",
      "url": "https://youtube.com/watch?v=9dX4h77PQV8",
      "tag": "trending"
    },
    {
      "rank": 5,
      "title": "Panchayat Season 4 - Official Teaser | Jitendra Kumar, Neena Gupta, Raghubir Yadav | Prime Video IN",
      "channel": "Prime Video India",
      "views": "3.7M",
      "likes": "144.5k",
      "url": "https://youtube.com/watch?v=URBN7HNf7T4",
      "tag": "trending"
    },
    {
      "rank": 6,
      "title": "Siragadikka Aasai | 5th to 10th May 2025 - Promo",
      "channel": "Vijay Television",
      "views": "2.4M",
      "likes": "37.4k",
      "url": "https://youtube.com/watch?v=jyaIHKWKoec",
      "tag": "trending"
    },
    {
      "rank": 7,
      "title": "Mahanadhi | 5th to 9th May 2025 - Promo",
      "channel": "Vijay Television",
      "views": "3.3M",
      "likes": "78.2k",
      "url": "https://youtube.com/watch?v=8ScgQ31eXsI",
      "tag": "trending"
    },
    {
      "rank": 8,
      "title": "BUILDING A CAR IN REAL LIFE #2",
      "channel": "TechShot",
      "views": "1.8M",
      "likes": "65.4k",
      "url": "https://youtube.com/watch?v=xnDbTcUUpLU",
      "tag": "trending"
    },
    {
      "rank": 9,
      "title": "Ayyanar Thunai | 5th to 10th May 2025 - Promo",
      "channel": "Vijay Television",
      "views": "2.2M",
      "likes": "36.4k",
      "url": "https://youtube.com/watch?v=J37QIzH9PCQ",
      "tag": "trending"
    },
    {
      "rank": 10,
      "title": "HACKER LEVEL! SOLO VS SQUAD GAMEPLAY | GARENA FREE FIRE",
      "channel": "Total Gaming",
      "views": "1.9M",
      "likes": "218.5k",
      "url": "https://youtube.com/watch?v=8iZ8XOUybIc",
      "tag": "trending"
    },
    {
      "rank": 11,
      "title": "Hridayam Lopala Full Video Song| Kingdom | Vijay Deverakonda | Anirudh Ravichander |Gowtam Tinnanuri",
      "channel": "Aditya Music",
      "views": "5.7M",
      "likes": "114.6k",
      "url": "https://youtube.com/watch?v=Q1iskzwrcFU",
      "tag": "trending"
    },
    {
      "rank": 12,
      "title": "Dream VS Daquavis $100,000 PvP Duel",
      "channel": "Dream",
      "views": "5.4M",
      "likes": "431.1k",
      "url": "https://youtube.com/watch?v=hlTGjc7Gn04",
      "tag": "trending"
    },
    {
      "rank": 13,
      "title": "Kondattam Video | Thudarum | Mohanlal, Shobana, Jakes Bejoy, Tharun Moorthy, MRenjith | MG SREEKUMAR",
      "channel": "Sony Music South",
      "views": "4.8M",
      "likes": "190.4k",
      "url": "https://youtube.com/watch?v=n_gisO-mT14",
      "tag": "trending"
    },
    {
      "rank": 14,
      "title": "Teacher You Tube Live Session",
      "channel": " NIPUN Bharat | Uttar Pradesh",
      "views": "252.7k",
      "likes": "18.9k",
      "url": "https://youtube.com/watch?v=6bMVSkMTEms",
      "tag": "trending"
    },
    {
      "rank": 15,
      "title": "Maaman - Official Trailer | Soori | Aishwarya Lekshmi | Prasanth Pandiyaraj | Hesham Abdul Wahab",
      "channel": "Think Music India",
      "views": "4.8M",
      "likes": "111.4k",
      "url": "https://youtube.com/watch?v=RFxRhOVGp4U",
      "tag": "trending"
    },
    {
      "rank": 16,
      "title": "Retro Roast | Plip Plip",
      "channel": "Plip Plip",
      "views": "259.1k",
      "likes": "13.2k",
      "url": "https://youtube.com/watch?v=Wleby2uqYDE",
      "tag": "trending"
    },
    {
      "rank": 17,
      "title": "Housefull 5 | Official Teaser | Sajid Nadiadwala | Tarun Mansukhani | In Cinemas on 6th June 2025",
      "channel": "NadiadwalaGrandson",
      "views": "8.0M",
      "likes": "253.8k",
      "url": "https://youtube.com/watch?v=e2eX1HGeBFE",
      "tag": "trending"
    },
    {
      "rank": 18,
      "title": "Find the Invisible Man Challenge!",
      "channel": "Mythpat",
      "views": "1.1M",
      "likes": "37.8k",
      "url": "https://youtube.com/watch?v=wmY4FDPBwSU",
      "tag": "trending"
    },
    {
      "rank": 19,
      "title": "#Dayangaram VJ Siddhu - 01 | Title Announcement | Ishari K Ganesh | Vels Film International",
      "channel": "Vels Film International",
      "views": "1.9M",
      "likes": "38.8k",
      "url": "https://youtube.com/watch?v=NKitkaIi7vY",
      "tag": "trending"
    },
    {
      "rank": 20,
      "title": "#HotstarSpecials #HeartBeatSeason2 | Promo | #HeartBeat2 ComingSoon on #jiohotstar",
      "channel": "JioHotstar Tamil",
      "views": "1.9M",
      "likes": "30.8k",
      "url": "https://youtube.com/watch?v=ezTbBUkUzgY",
      "tag": "trending"
    },
    {
      "rank": 21,
      "title": "Official Teaser | The World of Prince | Prince and Family | Dilieep | Listin\u00a0Stephen",
      "channel": "Magic Frames",
      "views": "522.9k",
      "likes": "16.6k",
      "url": "https://youtube.com/watch?v=LZz-a2GVcIo",
      "tag": "trending"
    },
    {
      "rank": 22,
      "title": "\u0c06\u0c24\u0c4d\u0c2e\u0c40\u0c2f\u0c41\u0c32 \u0c2e\u0c27\u0c4d\u0c2f Ricky \u0c27\u0c4b\u0c24\u0c3f  Function || Manjula Nirupam || Strikers",
      "channel": "Manjula Nirupam",
      "views": "1.0M",
      "likes": "10.4k",
      "url": "https://youtube.com/watch?v=DCvonIH-gQQ",
      "tag": "trending"
    },
    {
      "rank": 23,
      "title": "\u0d12\u0d30\u0d41 \u0d1a\u0d3f\u0d30\u0d3f \u0d2c\u0d2e\u0d4d\u0d2a\u0d7c \u0d1a\u0d3f\u0d30\u0d3f\u0d2f\u0d3f\u0d7d \u0d28\u0d3f\u0d28\u0d4d\u0d28\u0d4d \u0d2e\u0d3e\u0d31\u0d3e\u0d7b \u0d15\u0d3e\u0d30\u0d23\u0d02 Sumi Ajith Interview | Ithu Item Vere  |",
      "channel": "Breakthrough",
      "views": "171.1k",
      "likes": "1.2k",
      "url": "https://youtube.com/watch?v=v-t39ruE0q0",
      "tag": "trending"
    },
    {
      "rank": 24,
      "title": "Getti Melam (\u0b95\u0bc6\u0b9f\u0bcd\u0b9f\u0bbf \u0bae\u0bc7\u0bb3\u0bae\u0bcd) | Mon-Fri, 7:30 PM | 04 May 25 | Promo | Zee Tamil",
      "channel": "Zee Tamil",
      "views": "956.5k",
      "likes": "17.0k",
      "url": "https://youtube.com/watch?v=TZDfLWEulKE",
      "tag": "trending"
    },
    {
      "rank": 25,
      "title": "Yaad Teri Aati Hai | Afsana Pyar Ka | Aamir Khan, Neelam | Alka Yagnik | Bollywood 90s Sad Love Song",
      "channel": "90's Gaane",
      "views": "201.2k",
      "likes": "655",
      "url": "https://youtube.com/watch?v=R3DrT1MoJd4",
      "tag": "trending"
    },
    {
      "rank": 26,
      "title": "\u0938\u092c\u0938\u0947 \u092c\u095c\u0940 \u092a\u0947\u0902\u0938\u093f\u0932 \u270f\ufe0f WORLD'S BIGGEST PENCIL | Pakau TV Channel",
      "channel": "Pakau TV channel",
      "views": "84.3k",
      "likes": "1.5k",
      "url": "https://youtube.com/watch?v=hReg46Vwvq0",
      "tag": "trending"
    },
    {
      "rank": 27,
      "title": "\u0b87\u0bb0\u0bc1\u0ba8\u0bcd\u0ba4\u0bbe\u0bb2\u0bc1\u0bae\u0bcd \u0b92\u0bb0\u0bc1 \u0ba8\u0bbf\u0baf\u0bbe\u0baf\u0bae\u0bcd \u0bb5\u0bc7\u0ba3\u0bbe\u0bae\u0bbe da?\ud83d\ude12\ud83d\ude41 | Delhi Series | EP - 05 | Vj Siddhu Vlogs",
      "channel": "Vj Siddhu Vlogs",
      "views": "1.6M",
      "likes": "113.7k",
      "url": "https://youtube.com/watch?v=_fSgUNXDq78",
      "tag": "trending"
    },
    {
      "rank": 28,
      "title": "WB Madhyamik Result 2025: \u09b8\u09cd\u09ac\u09aa\u09cd\u09a8 \u09a6\u09c7\u0996\u09c7\u0993 \u09b6\u09c7\u09b7, \u09ad\u09be\u09b2\u09cb \u09ab\u09b2 \u09ae\u09c3\u09a4 \u09a5\u09c8\u09ac\u09bf\u09b0! \u09b9\u09be\u09b9\u09be\u0995\u09be\u09b0 \u0986\u09b8\u09be\u09a8\u09b8\u09cb\u09b2\u09c7\u09b0 \u09ae\u09c1\u0996\u09cb\u09aa\u09be\u09a7\u09cd\u09af\u09be\u09df \u09aa\u09b0\u09bf\u09ac\u09be\u09b0\u09c7",
      "channel": "Sangbad Pratidin",
      "views": "991.8k",
      "likes": "7.7k",
      "url": "https://youtube.com/watch?v=DZDzCzGLG0I",
      "tag": "trending"
    },
    {
      "rank": 29,
      "title": "Maroon 5 - Priceless ft. LISA (Official Video)",
      "channel": "Maroon5VEVO",
      "views": "8.3M",
      "likes": "587.3k",
      "url": "https://youtube.com/watch?v=vaGf8fmtBr4",
      "tag": "trending"
    },
    {
      "rank": 30,
      "title": "Kunali Riding Police Bike \ud83d\ude0d",
      "channel": "Sourav Joshi Vlogs",
      "views": "3.5M",
      "likes": "162.3k",
      "url": "https://youtube.com/watch?v=9AxsIu6yTRE",
      "tag": "trending"
    }
  ],
  "last_updated": "2025-05-05 05:31:11 IST"
}